mkdocs_simple/__init__.py
mkdocs_simple/__main__.py
mkdocs_simple/_version.py
mkdocs_simple/cli/__init__.py
mkdocs_simple/cli/app.py
mkdocs_simple/gitlab.py
mkdocs_simple/plugin.py
mkdocs_simple/py.typed
mkdocs_simple/site_config.py
mkdocs_simple-0.0.1.dist-info/LICENSE
mkdocs_simple-0.0.1.dist-info/WHEEL
mkdocs_simple-0.0.1.dist-info/entry_points.txt
mkdocs_simple-0.0.1.dist-info/METADATA
mkdocs_simple-0.0.1.dist-info/RECORD
