Metadata-Version: 2.1
Name: mkdocs-simple
Version: 0.0.1
Summary: 
Home-page: https://pypi.org/project/mkdocs-simple
License: MIT
Author: Danil Akhtarov
Author-email: daxartio@gmail.com
Requires-Python: >=3.8,<4.0
Classifier: License :: OSI Approved :: MIT License
Classifier: Programming Language :: Python :: 3
Classifier: Programming Language :: Python :: 3.8
Classifier: Programming Language :: Python :: 3.9
Classifier: Programming Language :: Python :: 3.10
Classifier: Programming Language :: Python :: 3.11
Project-URL: Repository, https://github.com/daxartio/mkdocs-simple
